pyiides/__init__.py
pyiides/pyiides.py
pyiides-0.2.0.dist-info/licenses/LICENSE.txt
pyiides-0.2.0.dist-info/METADATA
pyiides-0.2.0.dist-info/WHEEL
pyiides-0.2.0.dist-info/top_level.txt
pyiides-0.2.0.dist-info/RECORD
