Metadata-Version: 2.4
Name: pyiides
Version: 0.2.0
Summary: A Python implementation of the Insider Incident Data Exchange Standard (IIDES)
Home-page: https://github.com/cmu-sei/pyiides
Author: Software Engineering Institute
Author-email: abwhisnant@sei.cmu.edu
License: LICENSE.txt
Classifier: Programming Language :: Python :: 3
Classifier: Operating System :: OS Independent
Requires-Python: >=3.9
License-File: LICENSE.txt
Dynamic: author
Dynamic: author-email
Dynamic: classifier
Dynamic: description
Dynamic: description-content-type
Dynamic: home-page
Dynamic: license
Dynamic: license-file
Dynamic: requires-python
Dynamic: summary
